{
    "sourceFile": "src/pages/Home.tsx",
    "activeCommit": 0,
    "commits": [
        {
            "activePatchIndex": 28,
            "patches": [
                {
                    "date": 1755347748704,
                    "content": "Index: \n===================================================================\n--- \n+++ \n"
                },
                {
                    "date": 1755347919402,
                    "content": "Index: \n===================================================================\n--- \n+++ \n@@ -34,9 +34,9 @@\n           fontSize: '1.125rem',\n           margin: 'var(--space-2) 0 0 0',\n           fontWeight: 500,\n         }}>\n-          Your pocket-sized trading terminal\n+          Your pocket-sized charting terminal\n         </p>\n       </div>\n \n       {/* Search Section */}\n"
                },
                {
                    "date": 1755347932868,
                    "content": "Index: \n===================================================================\n--- \n+++ \n@@ -34,9 +34,9 @@\n           fontSize: '1.125rem',\n           margin: 'var(--space-2) 0 0 0',\n           fontWeight: 500,\n         }}>\n-          Your pocket-sized charting terminal\n+          Your pocket-sized DEX terminal\n         </p>\n       </div>\n \n       {/* Search Section */}\n@@ -47,9 +47,9 @@\n           fontSize: '0.875rem',\n           textAlign: 'center',\n           margin: 'var(--space-3) 0 0 0',\n         }}>\n-          Search tokens by name or paste any token address\n+          Search tokens by token address\n         </p>\n       </div>\n \n       {/* Feature highlights */}\n"
                },
                {
                    "date": 1755347959527,
                    "content": "Index: \n===================================================================\n--- \n+++ \n@@ -47,9 +47,9 @@\n           fontSize: '0.875rem',\n           textAlign: 'center',\n           margin: 'var(--space-3) 0 0 0',\n         }}>\n-          Search tokens by token address\n+          Search tokens by address or name\n         </p>\n       </div>\n \n       {/* Feature highlights */}\n@@ -96,9 +96,9 @@\n             color: 'var(--text-muted)', \n             margin: 0,\n             lineHeight: 1.4,\n           }}>\n-            Optimized for Telegram mini apps\n+            Optimized for Telegram \n           </p>\n         </div>\n \n         <div className=\"card-compact\" style={{ textAlign: 'center' }}>\n"
                },
                {
                    "date": 1755347967048,
                    "content": "Index: \n===================================================================\n--- \n+++ \n@@ -96,9 +96,9 @@\n             color: 'var(--text-muted)', \n             margin: 0,\n             lineHeight: 1.4,\n           }}>\n-            Optimized for Telegram \n+            Optimized for Telegram Mobile\n           </p>\n         </div>\n \n         <div className=\"card-compact\" style={{ textAlign: 'center' }}>\n"
                },
                {
                    "date": 1755347978456,
                    "content": "Index: \n===================================================================\n--- \n+++ \n@@ -96,9 +96,9 @@\n             color: 'var(--text-muted)', \n             margin: 0,\n             lineHeight: 1.4,\n           }}>\n-            Optimized for Telegram Mobile\n+            Optimized for Telegram in-app use\n           </p>\n         </div>\n \n         <div className=\"card-compact\" style={{ textAlign: 'center' }}>\n"
                },
                {
                    "date": 1755347992978,
                    "content": "Index: \n===================================================================\n--- \n+++ \n@@ -1,6 +1,7 @@\n import SearchInput from '../features/search/SearchInput';\n \n+\n export default function Home() {\n   return (\n     <div\n       style={{\n"
                },
                {
                    "date": 1755348000050,
                    "content": "Index: \n===================================================================\n--- \n+++ \n@@ -1,7 +1,7 @@\n import SearchInput from '../features/search/SearchInput';\n+// Import MUI components\n \n-\n export default function Home() {\n   return (\n     <div\n       style={{\n"
                },
                {
                    "date": 1755348052514,
                    "content": "Index: \n===================================================================\n--- \n+++ \n@@ -1,6 +1,6 @@\n import SearchInput from '../features/search/SearchInput';\n-// Import MUI components\n+// Import MUI components: ElectricBolt, \n \n export default function Home() {\n   return (\n     <div\n"
                },
                {
                    "date": 1755348060218,
                    "content": "Index: \n===================================================================\n--- \n+++ \n@@ -1,6 +1,6 @@\n import SearchInput from '../features/search/SearchInput';\n-// Import MUI components: ElectricBolt, \n+// Import MUI icon-material: ElectricBolt, \n \n export default function Home() {\n   return (\n     <div\n"
                },
                {
                    "date": 1755348085268,
                    "content": "Index: \n===================================================================\n--- \n+++ \n@@ -1,6 +1,6 @@\n import SearchInput from '../features/search/SearchInput';\n-// Import MUI icon-material: ElectricBolt, \n+// Import MUI icon-material: ElectricBolt, MobileFriendly, \n \n export default function Home() {\n   return (\n     <div\n"
                },
                {
                    "date": 1755348214908,
                    "content": "Index: \n===================================================================\n--- \n+++ \n@@ -1,6 +1,6 @@\n import SearchInput from '../features/search/SearchInput';\n-// Import MUI icon-material: ElectricBolt, MobileFriendly, \n+// Import MUI icon-material: ElectricBolt, MobileFriendly, Pol\n \n export default function Home() {\n   return (\n     <div\n"
                },
                {
                    "date": 1755348254673,
                    "content": "Index: \n===================================================================\n--- \n+++ \n@@ -1,6 +1,7 @@\n import SearchInput from '../features/search/SearchInput';\n-// Import MUI icon-material: ElectricBolt, MobileFriendly, Pol\n+// Import MUI icon-material: ElectricBolt, MobileFriendly, Polyline\n+import {}\n \n export default function Home() {\n   return (\n     <div\n"
                },
                {
                    "date": 1755348292561,
                    "content": "Index: \n===================================================================\n--- \n+++ \n@@ -1,7 +1,7 @@\n import SearchInput from '../features/search/SearchInput';\n // Import MUI icon-material: ElectricBolt, MobileFriendly, Polyline\n-import {}\n+import { ElectricBolt, MobileFriendly, Polyline } from '@mui/icons-material';\n \n export default function Home() {\n   return (\n     <div\n@@ -63,9 +63,11 @@\n         maxWidth: '800px',\n         marginTop: 'var(--space-6)',\n       }}>\n         <div className=\"card-compact\" style={{ textAlign: 'center' }}>\n-          <div style={{ fontSize: '2rem', marginBottom: 'var(--space-2)' }}>⚡</div>\n+          <div style={{ fontSize: '2rem', marginBottom: 'var(--space-2)' }}>\n+            \n+          </div>\n           <h3 style={{ \n             fontSize: '1rem', \n             fontWeight: 600, \n             margin: '0 0 var(--space-1) 0',\n"
                },
                {
                    "date": 1755348301227,
                    "content": "Index: \n===================================================================\n--- \n+++ \n@@ -64,9 +64,9 @@\n         marginTop: 'var(--space-6)',\n       }}>\n         <div className=\"card-compact\" style={{ textAlign: 'center' }}>\n           <div style={{ fontSize: '2rem', marginBottom: 'var(--space-2)' }}>\n-            \n+            <ElectricBolt sx={{ fontSize: 48 }} />\n           </div>\n           <h3 style={{ \n             fontSize: '1rem', \n             fontWeight: 600, \n"
                },
                {
                    "date": 1755348308119,
                    "content": "Index: \n===================================================================\n--- \n+++ \n@@ -85,9 +85,11 @@\n           </p>\n         </div>\n \n         <div className=\"card-compact\" style={{ textAlign: 'center' }}>\n-          <div style={{ fontSize: '2rem', marginBottom: 'var(--space-2)' }}>📱</div>\n+          <div style={{ fontSize: '2rem', marginBottom: 'var(--space-2)' }}>\n+            \n+          </div>\n           <h3 style={{ \n             fontSize: '1rem', \n             fontWeight: 600, \n             margin: '0 0 var(--space-1) 0',\n"
                },
                {
                    "date": 1755348314515,
                    "content": "Index: \n===================================================================\n--- \n+++ \n@@ -86,9 +86,9 @@\n         </div>\n \n         <div className=\"card-compact\" style={{ textAlign: 'center' }}>\n           <div style={{ fontSize: '2rem', marginBottom: 'var(--space-2)' }}>\n-            \n+            <MobileFriendly sx={{ fontSize: 48 }} />\n           </div>\n           <h3 style={{ \n             fontSize: '1rem', \n             fontWeight: 600, \n@@ -107,9 +107,11 @@\n           </p>\n         </div>\n \n         <div className=\"card-compact\" style={{ textAlign: 'center' }}>\n-          <div style={{ fontSize: '2rem', marginBottom: 'var(--space-2)' }}>🔗</div>\n+          <div style={{ fontSize: '2rem', marginBottom: 'var(--space-2)' }}>\n+            <Polyline sx={{ fontSize: 48 }} />\n+          </div>\n           <h3 style={{ \n             fontSize: '1rem', \n             fontWeight: 600, \n             margin: '0 0 var(--space-1) 0',\n"
                },
                {
                    "date": 1755348326266,
                    "content": "Index: \n===================================================================\n--- \n+++ \n@@ -64,9 +64,9 @@\n         marginTop: 'var(--space-6)',\n       }}>\n         <div className=\"card-compact\" style={{ textAlign: 'center' }}>\n           <div style={{ fontSize: '2rem', marginBottom: 'var(--space-2)' }}>\n-            <ElectricBolt sx={{ fontSize: 48 }} />\n+            <ElectricBolt sx={{ fontSize: 48, c }} />\n           </div>\n           <h3 style={{ \n             fontSize: '1rem', \n             fontWeight: 600, \n"
                },
                {
                    "date": 1755348335298,
                    "content": "Index: \n===================================================================\n--- \n+++ \n@@ -64,9 +64,9 @@\n         marginTop: 'var(--space-6)',\n       }}>\n         <div className=\"card-compact\" style={{ textAlign: 'center' }}>\n           <div style={{ fontSize: '2rem', marginBottom: 'var(--space-2)' }}>\n-            <ElectricBolt sx={{ fontSize: 48, c }} />\n+            <ElectricBolt sx={{ fontSize: 48, color: 'var(--accent-telegram)' }} />\n           </div>\n           <h3 style={{ \n             fontSize: '1rem', \n             fontWeight: 600, \n"
                },
                {
                    "date": 1755348350727,
                    "content": "Index: \n===================================================================\n--- \n+++ \n@@ -0,0 +1,146 @@\n+import SearchInput from '../features/search/SearchInput';\n+// Import MUI icon-material: ElectricBolt, MobileFriendly, Polyline\n+import { ElectricBolt, MobileFriendly, Polyline } from '@mui/icons-material';\n+\n+export default function Home() {\n+  return (\n+    <div\n+      style={{\n+        height: '100vh',\n+        display: 'flex',\n+        flexDirection: 'column',\n+        alignItems: 'center',\n+        justifyContent: 'center',\n+        gap: 'var(--space-6)',\n+        padding: 'var(--space-4)',\n+        background: 'linear-gradient(135deg, var(--bg) 0%, var(--bg-elev) 100%)',\n+      }}\n+    >\n+      {/* Logo and Brand */}\n+      <div style={{ textAlign: 'center', marginBottom: 'var(--space-4)' }}>\n+        <h1 \n+          style={{ \n+            fontSize: '3rem', \n+            fontWeight: 800, \n+            margin: 0,\n+            background: 'linear-gradient(135deg, var(--telegram-blue) 0%, var(--brand-secondary) 100%)',\n+            WebkitBackgroundClip: 'text',\n+            WebkitTextFillColor: 'transparent',\n+            backgroundClip: 'text',\n+          }}\n+        >\n+          SmallDEX\n+        </h1>\n+        <p style={{ \n+          color: 'var(--text-secondary)', \n+          fontSize: '1.125rem',\n+          margin: 'var(--space-2) 0 0 0',\n+          fontWeight: 500,\n+        }}>\n+          Your pocket-sized DEX terminal\n+        </p>\n+      </div>\n+\n+      {/* Search Section */}\n+      <div style={{ width: '100%', maxWidth: '600px' }}>\n+        <SearchInput autoFocus large />\n+        <p style={{ \n+          color: 'var(--text-muted)', \n+          fontSize: '0.875rem',\n+          textAlign: 'center',\n+          margin: 'var(--space-3) 0 0 0',\n+        }}>\n+          Search tokens by address or name\n+        </p>\n+      </div>\n+\n+      {/* Feature highlights */}\n+      <div style={{ \n+        display: 'grid', \n+        gridTemplateColumns: 'repeat(auto-fit, minmax(200px, 1fr))',\n+        gap: 'var(--space-4)',\n+        width: '100%',\n+        maxWidth: '800px',\n+        marginTop: 'var(--space-6)',\n+      }}>\n+        <div className=\"card-compact\" style={{ textAlign: 'center' }}>\n+          <div style={{ fontSize: '2rem', marginBottom: 'var(--space-2)' }}>\n+            <ElectricBolt sx={{ fontSize: 48, backgcolor: 'var(--accent-telegram)' }} />\n+          </div>\n+          <h3 style={{ \n+            fontSize: '1rem', \n+            fontWeight: 600, \n+            margin: '0 0 var(--space-1) 0',\n+            color: 'var(--text)',\n+          }}>\n+            Lightning Fast\n+          </h3>\n+          <p style={{ \n+            fontSize: '0.875rem', \n+            color: 'var(--text-muted)', \n+            margin: 0,\n+            lineHeight: 1.4,\n+          }}>\n+            Real-time data from multiple DEX sources\n+          </p>\n+        </div>\n+\n+        <div className=\"card-compact\" style={{ textAlign: 'center' }}>\n+          <div style={{ fontSize: '2rem', marginBottom: 'var(--space-2)' }}>\n+            <MobileFriendly sx={{ fontSize: 48 }} />\n+          </div>\n+          <h3 style={{ \n+            fontSize: '1rem', \n+            fontWeight: 600, \n+            margin: '0 0 var(--space-1) 0',\n+            color: 'var(--text)',\n+          }}>\n+            Mobile First\n+          </h3>\n+          <p style={{ \n+            fontSize: '0.875rem', \n+            color: 'var(--text-muted)', \n+            margin: 0,\n+            lineHeight: 1.4,\n+          }}>\n+            Optimized for Telegram in-app use\n+          </p>\n+        </div>\n+\n+        <div className=\"card-compact\" style={{ textAlign: 'center' }}>\n+          <div style={{ fontSize: '2rem', marginBottom: 'var(--space-2)' }}>\n+            <Polyline sx={{ fontSize: 48 }} />\n+          </div>\n+          <h3 style={{ \n+            fontSize: '1rem', \n+            fontWeight: 600, \n+            margin: '0 0 var(--space-1) 0',\n+            color: 'var(--text)',\n+          }}>\n+            Multi-Chain\n+          </h3>\n+          <p style={{ \n+            fontSize: '0.875rem', \n+            color: 'var(--text-muted)', \n+            margin: 0,\n+            lineHeight: 1.4,\n+          }}>\n+            Support for all major networks\n+          </p>\n+        </div>\n+      </div>\n+\n+      {/* Footer info */}\n+      <div style={{ \n+        position: 'absolute',\n+        bottom: 'var(--space-6)',\n+        color: 'var(--text-disabled)',\n+        fontSize: '0.75rem',\n+        textAlign: 'center',\n+      }}>\n+        Powered by GeckoTerminal, DexScreener & CoinGecko\n+      </div>\n+    </div>\n+  );\n+}\n+\n"
                },
                {
                    "date": 1755348362220,
                    "content": "Index: \n===================================================================\n--- \n+++ \n@@ -64,9 +64,9 @@\n         marginTop: 'var(--space-6)',\n       }}>\n         <div className=\"card-compact\" style={{ textAlign: 'center' }}>\n           <div style={{ fontSize: '2rem', marginBottom: 'var(--space-2)' }}>\n-            <ElectricBolt sx={{ fontSize: 48, backgcolor: 'var(--accent-telegram)' }} />\n+            <ElectricBolt sx={{ fontSize: 48 }} />\n           </div>\n           <h3 style={{ \n             fontSize: '1rem', \n             fontWeight: 600, \n@@ -143,150 +143,4 @@\n     </div>\n   );\n }\n \n-import SearchInput from '../features/search/SearchInput';\n-// Import MUI icon-material: ElectricBolt, MobileFriendly, Polyline\n-import { ElectricBolt, MobileFriendly, Polyline } from '@mui/icons-material';\n-\n-export default function Home() {\n-  return (\n-    <div\n-      style={{\n-        height: '100vh',\n-        display: 'flex',\n-        flexDirection: 'column',\n-        alignItems: 'center',\n-        justifyContent: 'center',\n-        gap: 'var(--space-6)',\n-        padding: 'var(--space-4)',\n-        background: 'linear-gradient(135deg, var(--bg) 0%, var(--bg-elev) 100%)',\n-      }}\n-    >\n-      {/* Logo and Brand */}\n-      <div style={{ textAlign: 'center', marginBottom: 'var(--space-4)' }}>\n-        <h1 \n-          style={{ \n-            fontSize: '3rem', \n-            fontWeight: 800, \n-            margin: 0,\n-            background: 'linear-gradient(135deg, var(--telegram-blue) 0%, var(--brand-secondary) 100%)',\n-            WebkitBackgroundClip: 'text',\n-            WebkitTextFillColor: 'transparent',\n-            backgroundClip: 'text',\n-          }}\n-        >\n-          SmallDEX\n-        </h1>\n-        <p style={{ \n-          color: 'var(--text-secondary)', \n-          fontSize: '1.125rem',\n-          margin: 'var(--space-2) 0 0 0',\n-          fontWeight: 500,\n-        }}>\n-          Your pocket-sized DEX terminal\n-        </p>\n-      </div>\n-\n-      {/* Search Section */}\n-      <div style={{ width: '100%', maxWidth: '600px' }}>\n-        <SearchInput autoFocus large />\n-        <p style={{ \n-          color: 'var(--text-muted)', \n-          fontSize: '0.875rem',\n-          textAlign: 'center',\n-          margin: 'var(--space-3) 0 0 0',\n-        }}>\n-          Search tokens by address or name\n-        </p>\n-      </div>\n-\n-      {/* Feature highlights */}\n-      <div style={{ \n-        display: 'grid', \n-        gridTemplateColumns: 'repeat(auto-fit, minmax(200px, 1fr))',\n-        gap: 'var(--space-4)',\n-        width: '100%',\n-        maxWidth: '800px',\n-        marginTop: 'var(--space-6)',\n-      }}>\n-        <div className=\"card-compact\" style={{ textAlign: 'center' }}>\n-          <div style={{ fontSize: '2rem', marginBottom: 'var(--space-2)' }}>\n-            <ElectricBolt sx={{ fontSize: 48, color: 'var(--accent-telegram)' }} />\n-          </div>\n-          <h3 style={{ \n-            fontSize: '1rem', \n-            fontWeight: 600, \n-            margin: '0 0 var(--space-1) 0',\n-            color: 'var(--text)',\n-          }}>\n-            Lightning Fast\n-          </h3>\n-          <p style={{ \n-            fontSize: '0.875rem', \n-            color: 'var(--text-muted)', \n-            margin: 0,\n-            lineHeight: 1.4,\n-          }}>\n-            Real-time data from multiple DEX sources\n-          </p>\n-        </div>\n-\n-        <div className=\"card-compact\" style={{ textAlign: 'center' }}>\n-          <div style={{ fontSize: '2rem', marginBottom: 'var(--space-2)' }}>\n-            <MobileFriendly sx={{ fontSize: 48 }} />\n-          </div>\n-          <h3 style={{ \n-            fontSize: '1rem', \n-            fontWeight: 600, \n-            margin: '0 0 var(--space-1) 0',\n-            color: 'var(--text)',\n-          }}>\n-            Mobile First\n-          </h3>\n-          <p style={{ \n-            fontSize: '0.875rem', \n-            color: 'var(--text-muted)', \n-            margin: 0,\n-            lineHeight: 1.4,\n-          }}>\n-            Optimized for Telegram in-app use\n-          </p>\n-        </div>\n-\n-        <div className=\"card-compact\" style={{ textAlign: 'center' }}>\n-          <div style={{ fontSize: '2rem', marginBottom: 'var(--space-2)' }}>\n-            <Polyline sx={{ fontSize: 48 }} />\n-          </div>\n-          <h3 style={{ \n-            fontSize: '1rem', \n-            fontWeight: 600, \n-            margin: '0 0 var(--space-1) 0',\n-            color: 'var(--text)',\n-          }}>\n-            Multi-Chain\n-          </h3>\n-          <p style={{ \n-            fontSize: '0.875rem', \n-            color: 'var(--text-muted)', \n-            margin: 0,\n-            lineHeight: 1.4,\n-          }}>\n-            Support for all major networks\n-          </p>\n-        </div>\n-      </div>\n-\n-      {/* Footer info */}\n-      <div style={{ \n-        position: 'absolute',\n-        bottom: 'var(--space-6)',\n-        color: 'var(--text-disabled)',\n-        fontSize: '0.75rem',\n-        textAlign: 'center',\n-      }}>\n-        Powered by GeckoTerminal, DexScreener & CoinGecko\n-      </div>\n-    </div>\n-  );\n-}\n-\n"
                },
                {
                    "date": 1755348372746,
                    "content": "Index: \n===================================================================\n--- \n+++ \n@@ -64,8 +64,9 @@\n         marginTop: 'var(--space-6)',\n       }}>\n         <div className=\"card-compact\" style={{ textAlign: 'center' }}>\n           <div style={{ fontSize: '2rem', marginBottom: 'var(--space-2)' }}>\n+            // add telegram color to the \n             <ElectricBolt sx={{ fontSize: 48 }} />\n           </div>\n           <h3 style={{ \n             fontSize: '1rem', \n"
                },
                {
                    "date": 1755348386592,
                    "content": "Index: \n===================================================================\n--- \n+++ \n@@ -64,9 +64,9 @@\n         marginTop: 'var(--space-6)',\n       }}>\n         <div className=\"card-compact\" style={{ textAlign: 'center' }}>\n           <div style={{ fontSize: '2rem', marginBottom: 'var(--space-2)' }}>\n-            // add telegram color to the \n+            {/* add telegram color to the icon */}\n             <ElectricBolt sx={{ fontSize: 48 }} />\n           </div>\n           <h3 style={{ \n             fontSize: '1rem', \n"
                },
                {
                    "date": 1755348396571,
                    "content": "Index: \n===================================================================\n--- \n+++ \n@@ -64,9 +64,9 @@\n         marginTop: 'var(--space-6)',\n       }}>\n         <div className=\"card-compact\" style={{ textAlign: 'center' }}>\n           <div style={{ fontSize: '2rem', marginBottom: 'var(--space-2)' }}>\n-            {/* add telegram color to the icon */}\n+            {/* add telegram color to the icon - \"color: 'var(--accent-telegram)'\" does not work so use  */}\n             <ElectricBolt sx={{ fontSize: 48 }} />\n           </div>\n           <h3 style={{ \n             fontSize: '1rem', \n"
                },
                {
                    "date": 1755348402549,
                    "content": "Index: \n===================================================================\n--- \n+++ \n@@ -64,9 +64,9 @@\n         marginTop: 'var(--space-6)',\n       }}>\n         <div className=\"card-compact\" style={{ textAlign: 'center' }}>\n           <div style={{ fontSize: '2rem', marginBottom: 'var(--space-2)' }}>\n-            {/* add telegram color to the icon - \"color: 'var(--accent-telegram)'\" does not work so use  */}\n+            {/* add telegram color to the icon - \"color: 'var(--accent-telegram)'\"  */}\n             <ElectricBolt sx={{ fontSize: 48 }} />\n           </div>\n           <h3 style={{ \n             fontSize: '1rem', \n"
                },
                {
                    "date": 1755348410757,
                    "content": "Index: \n===================================================================\n--- \n+++ \n@@ -64,9 +64,9 @@\n         marginTop: 'var(--space-6)',\n       }}>\n         <div className=\"card-compact\" style={{ textAlign: 'center' }}>\n           <div style={{ fontSize: '2rem', marginBottom: 'var(--space-2)' }}>\n-            {/* add telegram color to the icon - \"color: 'var(--accent-telegram)'\"  */}\n+            {/* add telegram color to the icon - the sx prop \"color: 'var(--accent-telegram)'\" does not work */}\n             <ElectricBolt sx={{ fontSize: 48 }} />\n           </div>\n           <h3 style={{ \n             fontSize: '1rem', \n"
                },
                {
                    "date": 1755348418025,
                    "content": "Index: \n===================================================================\n--- \n+++ \n@@ -64,9 +64,9 @@\n         marginTop: 'var(--space-6)',\n       }}>\n         <div className=\"card-compact\" style={{ textAlign: 'center' }}>\n           <div style={{ fontSize: '2rem', marginBottom: 'var(--space-2)' }}>\n-            {/* add telegram color to the icon - the sx prop \"color: 'var(--accent-telegram)'\" does not work */}\n+            {/* add telegram color to the icon - the sx prop \"color: 'var(--accent-telegram)'\" does not apply  */}\n             <ElectricBolt sx={{ fontSize: 48 }} />\n           </div>\n           <h3 style={{ \n             fontSize: '1rem', \n"
                },
                {
                    "date": 1755348427720,
                    "content": "Index: \n===================================================================\n--- \n+++ \n@@ -64,9 +64,9 @@\n         marginTop: 'var(--space-6)',\n       }}>\n         <div className=\"card-compact\" style={{ textAlign: 'center' }}>\n           <div style={{ fontSize: '2rem', marginBottom: 'var(--space-2)' }}>\n-            \n+        \n             <ElectricBolt sx={{ fontSize: 48 }} />\n           </div>\n           <h3 style={{ \n             fontSize: '1rem', \n"
                },
                {
                    "date": 1755348489191,
                    "content": "Index: \n===================================================================\n--- \n+++ \n@@ -0,0 +1,146 @@\n+import SearchInput from '../features/search/SearchInput';\n+// Import MUI icon-material: ElectricBolt, MobileFriendly, Polyline\n+import { ElectricBolt, MobileFriendly, Polyline } from '@mui/icons-material';\n+\n+export default function Home() {\n+  return (\n+    <div\n+      style={{\n+        height: '100vh',\n+        display: 'flex',\n+        flexDirection: 'column',\n+        alignItems: 'center',\n+        justifyContent: 'center',\n+        gap: 'var(--space-6)',\n+        padding: 'var(--space-4)',\n+        background: 'linear-gradient(135deg, var(--bg) 0%, var(--bg-elev) 100%)',\n+      }}\n+    >\n+      {/* Logo and Brand */}\n+      <div style={{ textAlign: 'center', marginBottom: 'var(--space-4)' }}>\n+        <h1 \n+          style={{ \n+            fontSize: '3rem', \n+            fontWeight: 800, \n+            margin: 0,\n+            background: 'linear-gradient(135deg, var(--telegram-blue) 0%, var(--brand-secondary) 100%)',\n+            WebkitBackgroundClip: 'text',\n+            WebkitTextFillColor: 'transparent',\n+            backgroundClip: 'text',\n+          }}\n+        >\n+          SmallDEX\n+        </h1>\n+        <p style={{ \n+          color: 'var(--text-secondary)', \n+          fontSize: '1.125rem',\n+          margin: 'var(--space-2) 0 0 0',\n+          fontWeight: 500,\n+        }}>\n+          Your pocket-sized DEX terminal\n+        </p>\n+      </div>\n+\n+      {/* Search Section */}\n+      <div style={{ width: '100%', maxWidth: '600px' }}>\n+        <SearchInput autoFocus large />\n+        <p style={{ \n+          color: 'var(--text-muted)', \n+          fontSize: '0.875rem',\n+          textAlign: 'center',\n+          margin: 'var(--space-3) 0 0 0',\n+        }}>\n+          Search tokens by address or name\n+        </p>\n+      </div>\n+\n+      {/* Feature highlights */}\n+      <div style={{ \n+        display: 'grid', \n+        gridTemplateColumns: 'repeat(auto-fit, minmax(200px, 1fr))',\n+        gap: 'var(--space-4)',\n+        width: '100%',\n+        maxWidth: '800px',\n+        marginTop: 'var(--space-6)',\n+      }}>\n+        <div className=\"card-compact\" style={{ textAlign: 'center' }}>\n+          <div style={{ fontSize: '2rem', marginBottom: 'var(--space-2)' }}>\n+            <ElectricBolt fill= 'var(--accent-telegram)' sx={{ fontSize: 48 }} />\n+          </div>\n+          <h3 style={{ \n+            fontSize: '1rem', \n+            fontWeight: 600, \n+            margin: '0 0 var(--space-1) 0',\n+            color: 'var(--text)',\n+          }}>\n+            Lightning Fast\n+          </h3>\n+          <p style={{ \n+            fontSize: '0.875rem', \n+            color: 'var(--text-muted)', \n+            margin: 0,\n+            lineHeight: 1.4,\n+          }}>\n+            Real-time data from multiple DEX sources\n+          </p>\n+        </div>\n+\n+        <div className=\"card-compact\" style={{ textAlign: 'center' }}>\n+          <div style={{ fontSize: '2rem', marginBottom: 'var(--space-2)' }}>\n+            <MobileFriendly sx={{ fontSize: 48 }} />\n+          </div>\n+          <h3 style={{ \n+            fontSize: '1rem', \n+            fontWeight: 600, \n+            margin: '0 0 var(--space-1) 0',\n+            color: 'var(--text)',\n+          }}>\n+            Mobile First\n+          </h3>\n+          <p style={{ \n+            fontSize: '0.875rem', \n+            color: 'var(--text-muted)', \n+            margin: 0,\n+            lineHeight: 1.4,\n+          }}>\n+            Optimized for Telegram in-app use\n+          </p>\n+        </div>\n+\n+        <div className=\"card-compact\" style={{ textAlign: 'center' }}>\n+          <div style={{ fontSize: '2rem', marginBottom: 'var(--space-2)' }}>\n+            <Polyline sx={{ fontSize: 48 }} />\n+          </div>\n+          <h3 style={{ \n+            fontSize: '1rem', \n+            fontWeight: 600, \n+            margin: '0 0 var(--space-1) 0',\n+            color: 'var(--text)',\n+          }}>\n+            Multi-Chain\n+          </h3>\n+          <p style={{ \n+            fontSize: '0.875rem', \n+            color: 'var(--text-muted)', \n+            margin: 0,\n+            lineHeight: 1.4,\n+          }}>\n+            Support for all major networks\n+          </p>\n+        </div>\n+      </div>\n+\n+      {/* Footer info */}\n+      <div style={{ \n+        position: 'absolute',\n+        bottom: 'var(--space-6)',\n+        color: 'var(--text-disabled)',\n+        fontSize: '0.75rem',\n+        textAlign: 'center',\n+      }}>\n+        Powered by GeckoTerminal, DexScreener & CoinGecko\n+      </div>\n+    </div>\n+  );\n+}\n+\n"
                }
            ],
            "date": 1755347748704,
            "name": "Commit-0",
            "content": "import SearchInput from '../features/search/SearchInput';\n\nexport default function Home() {\n  return (\n    <div\n      style={{\n        height: '100vh',\n        display: 'flex',\n        flexDirection: 'column',\n        alignItems: 'center',\n        justifyContent: 'center',\n        gap: 'var(--space-6)',\n        padding: 'var(--space-4)',\n        background: 'linear-gradient(135deg, var(--bg) 0%, var(--bg-elev) 100%)',\n      }}\n    >\n      {/* Logo and Brand */}\n      <div style={{ textAlign: 'center', marginBottom: 'var(--space-4)' }}>\n        <h1 \n          style={{ \n            fontSize: '3rem', \n            fontWeight: 800, \n            margin: 0,\n            background: 'linear-gradient(135deg, var(--telegram-blue) 0%, var(--brand-secondary) 100%)',\n            WebkitBackgroundClip: 'text',\n            WebkitTextFillColor: 'transparent',\n            backgroundClip: 'text',\n          }}\n        >\n          SmallDEX\n        </h1>\n        <p style={{ \n          color: 'var(--text-secondary)', \n          fontSize: '1.125rem',\n          margin: 'var(--space-2) 0 0 0',\n          fontWeight: 500,\n        }}>\n          Your pocket-sized trading terminal\n        </p>\n      </div>\n\n      {/* Search Section */}\n      <div style={{ width: '100%', maxWidth: '600px' }}>\n        <SearchInput autoFocus large />\n        <p style={{ \n          color: 'var(--text-muted)', \n          fontSize: '0.875rem',\n          textAlign: 'center',\n          margin: 'var(--space-3) 0 0 0',\n        }}>\n          Search tokens by name or paste any token address\n        </p>\n      </div>\n\n      {/* Feature highlights */}\n      <div style={{ \n        display: 'grid', \n        gridTemplateColumns: 'repeat(auto-fit, minmax(200px, 1fr))',\n        gap: 'var(--space-4)',\n        width: '100%',\n        maxWidth: '800px',\n        marginTop: 'var(--space-6)',\n      }}>\n        <div className=\"card-compact\" style={{ textAlign: 'center' }}>\n          <div style={{ fontSize: '2rem', marginBottom: 'var(--space-2)' }}>⚡</div>\n          <h3 style={{ \n            fontSize: '1rem', \n            fontWeight: 600, \n            margin: '0 0 var(--space-1) 0',\n            color: 'var(--text)',\n          }}>\n            Lightning Fast\n          </h3>\n          <p style={{ \n            fontSize: '0.875rem', \n            color: 'var(--text-muted)', \n            margin: 0,\n            lineHeight: 1.4,\n          }}>\n            Real-time data from multiple DEX sources\n          </p>\n        </div>\n\n        <div className=\"card-compact\" style={{ textAlign: 'center' }}>\n          <div style={{ fontSize: '2rem', marginBottom: 'var(--space-2)' }}>📱</div>\n          <h3 style={{ \n            fontSize: '1rem', \n            fontWeight: 600, \n            margin: '0 0 var(--space-1) 0',\n            color: 'var(--text)',\n          }}>\n            Mobile First\n          </h3>\n          <p style={{ \n            fontSize: '0.875rem', \n            color: 'var(--text-muted)', \n            margin: 0,\n            lineHeight: 1.4,\n          }}>\n            Optimized for Telegram mini apps\n          </p>\n        </div>\n\n        <div className=\"card-compact\" style={{ textAlign: 'center' }}>\n          <div style={{ fontSize: '2rem', marginBottom: 'var(--space-2)' }}>🔗</div>\n          <h3 style={{ \n            fontSize: '1rem', \n            fontWeight: 600, \n            margin: '0 0 var(--space-1) 0',\n            color: 'var(--text)',\n          }}>\n            Multi-Chain\n          </h3>\n          <p style={{ \n            fontSize: '0.875rem', \n            color: 'var(--text-muted)', \n            margin: 0,\n            lineHeight: 1.4,\n          }}>\n            Support for all major networks\n          </p>\n        </div>\n      </div>\n\n      {/* Footer info */}\n      <div style={{ \n        position: 'absolute',\n        bottom: 'var(--space-6)',\n        color: 'var(--text-disabled)',\n        fontSize: '0.75rem',\n        textAlign: 'center',\n      }}>\n        Powered by GeckoTerminal, DexScreener & CoinGecko\n      </div>\n    </div>\n  );\n}\n\n"
        }
    ]
}